{
    "date_and_time": "2024/03/06_14:21:16.308535",
    "start_time": "14:21:16",
    "measurement_time": "4.325050_s",
    "allowed_meas_pause": "0.000_s",
    "calculated_predelay": "0.000000_s",
    "calculated_measpause": "0.000000_s",
    "readout_and_check_time_bb": "14:21:16",
    "start_of_measurement_host_time": "14:21:11",
    "finish_of_measurement_host_time": "14:21:16",
    "start_of_measurement_mcir_time": "14:21:11",
    "finish_of_measurement_mcir_time": "14:21:16",
    "total_measurement_time_host": "4.796172_s",
    "total_measurement_time_mcir": "4.428468_s",
    "pause_after_measurement": "0.000000_s",
    "pause_averaging_time": "0.000000_s",
    "meas_uid": "352",
    "protocol_name": "adjcoilsens"
}