{
    "date_and_time": "2024/04/03_10:33:58.031510",
    "start_time": "10:33:58",
    "measurement_time": "0.800000_s",
    "allowed_meas_pause": "0.000_s",
    "calculated_predelay": "0.000000_s",
    "calculated_measpause": "0.000000_s",
    "readout_and_check_time_bb": "10:33:57",
    "start_of_measurement_host_time": "10:33:57",
    "finish_of_measurement_host_time": "10:33:58",
    "start_of_measurement_mcir_time": "10:33:57",
    "finish_of_measurement_mcir_time": "10:33:57",
    "total_measurement_time_host": "0.324133_s",
    "total_measurement_time_mcir": "0.245330_s",
    "pause_after_measurement": "0.000000_s",
    "pause_averaging_time": "0.000000_s",
    "meas_uid": "214",
    "protocol_name": "adjfre"
}