{
    "date_and_time": "2024/04/08_16:40:54.862368",
    "start_time": "16:40:54",
    "measurement_time": "0.800000_s",
    "allowed_meas_pause": "0.000_s",
    "calculated_predelay": "0.000000_s",
    "calculated_measpause": "0.000000_s",
    "readout_and_check_time_bb": "16:40:51",
    "start_of_measurement_host_time": "16:40:53",
    "finish_of_measurement_host_time": "16:40:54",
    "start_of_measurement_mcir_time": "16:40:50",
    "finish_of_measurement_mcir_time": "16:40:51",
    "total_measurement_time_host": "1.275588_s",
    "total_measurement_time_mcir": "1.193784_s",
    "pause_after_measurement": "0.000000_s",
    "pause_averaging_time": "0.000000_s",
    "meas_uid": "554",
    "protocol_name": "adjfre"
}