{
    "date_and_time": "2024/04/04_09:08:33.978751",
    "start_time": "09:08:33",
    "measurement_time": "3.600000_s",
    "allowed_meas_pause": "0.000_s",
    "calculated_predelay": "0.000000_s",
    "calculated_measpause": "0.000000_s",
    "readout_and_check_time_bb": "09:08:33",
    "start_of_measurement_host_time": "09:08:33",
    "finish_of_measurement_host_time": "09:08:33",
    "start_of_measurement_mcir_time": "09:08:32",
    "finish_of_measurement_mcir_time": "09:08:33",
    "total_measurement_time_host": "0.480714_s",
    "total_measurement_time_mcir": "0.401301_s",
    "pause_after_measurement": "0.000000_s",
    "pause_averaging_time": "0.000000_s",
    "meas_uid": "61",
    "protocol_name": "adjdico"
}