{
    "date_and_time": "2024/04/03_12:34:52.482734",
    "start_time": "12:34:52",
    "measurement_time": "0.306810_s",
    "allowed_meas_pause": "0.000_s",
    "calculated_predelay": "0.000000_s",
    "calculated_measpause": "0.000000_s",
    "readout_and_check_time_bb": "12:34:51",
    "start_of_measurement_host_time": "12:34:50",
    "finish_of_measurement_host_time": "12:34:52",
    "start_of_measurement_mcir_time": "12:34:49",
    "finish_of_measurement_mcir_time": "12:34:51",
    "total_measurement_time_host": "1.891938_s",
    "total_measurement_time_mcir": "1.809547_s",
    "pause_after_measurement": "0.000000_s",
    "pause_averaging_time": "0.000000_s",
    "meas_uid": "415",
    "protocol_name": "adjtra2d"
}