{
    "date_and_time": "2024/04/05_16:12:29.590003",
    "start_time": "16:12:29",
    "measurement_time": "20.719200_s",
    "allowed_meas_pause": "0.000_s",
    "calculated_predelay": "0.000000_s",
    "calculated_measpause": "0.000000_s",
    "readout_and_check_time_bb": "16:12:28",
    "start_of_measurement_host_time": "16:12:08",
    "finish_of_measurement_host_time": "16:12:29",
    "start_of_measurement_mcir_time": "16:12:07",
    "finish_of_measurement_mcir_time": "16:12:28",
    "total_measurement_time_host": "20.835297_s",
    "total_measurement_time_mcir": "20.749510_s",
    "pause_after_measurement": "0.000000_s",
    "pause_averaging_time": "0.000000_s",
    "meas_uid": "501",
    "protocol_name": "localizer"
}