{
    "date_and_time": "2024/03/26_12:48:48.642462",
    "start_time": "12:48:48",
    "measurement_time": "72.909930_s",
    "allowed_meas_pause": "60.000_s",
    "calculated_predelay": "0.000000_s",
    "calculated_measpause": "0.000000_s",
    "readout_and_check_time_bb": "12:48:49",
    "start_of_measurement_host_time": "12:47:35",
    "finish_of_measurement_host_time": "12:48:48",
    "start_of_measurement_mcir_time": "12:47:36",
    "finish_of_measurement_mcir_time": "12:48:49",
    "total_measurement_time_host": "73.020708_s",
    "total_measurement_time_mcir": "72.945553_s",
    "pause_after_measurement": "0.000000_s",
    "pause_averaging_time": "72.945553_s",
    "meas_uid": "329",
    "protocol_name": "t2_tse_tra_dr"
}