{
    "date_and_time": "2024/03/22_18:44:16.067430",
    "start_time": "18:44:16",
    "measurement_time": "3.600000_s",
    "allowed_meas_pause": "0.000_s",
    "calculated_predelay": "0.000000_s",
    "calculated_measpause": "0.000000_s",
    "readout_and_check_time_bb": "18:44:14",
    "start_of_measurement_host_time": "18:44:14",
    "finish_of_measurement_host_time": "18:44:16",
    "start_of_measurement_mcir_time": "18:44:13",
    "finish_of_measurement_mcir_time": "18:44:14",
    "total_measurement_time_host": "1.501983_s",
    "total_measurement_time_mcir": "0.226060_s",
    "pause_after_measurement": "0.000000_s",
    "pause_averaging_time": "0.000000_s",
    "meas_uid": "660",
    "protocol_name": "adjdico"
}